lsqfit-13.3.1.dist-info/RECORD
lsqfit-13.3.1.dist-info/WHEEL
lsqfit-13.3.1.dist-info/top_level.txt
lsqfit-13.3.1.dist-info/METADATA
lsqfit-13.3.1.dist-info/licenses/LICENSE.txt
lsqfit/_utilities.cpython-313-darwin.so
lsqfit/_version.py
lsqfit/__init__.py
lsqfit/_scipy.py
lsqfit/_extras.py
