Metadata-Version: 2.4
Name: lsqfit
Version: 13.3.1
Summary: Utilities for nonlinear least-squares fits.
Home-page: https://github.com/gplepage/lsqfit
Author: G. Peter Lepage
Author-email: g.p.lepage@cornell.edu
License: GPLv3
Requires-Python: >=3.9
License-File: LICENSE.txt
Requires-Dist: numpy>=1.24
Requires-Dist: gvar>=13.1.5
Requires-Dist: vegas>=6.1
Dynamic: license-file
